{
  "version": "5",
  "dialect": "mysql",
  "id": "794cc0d1-1adb-49d9-8580-cbd61d3a74af",
  "prevId": "82fb92e6-1cad-4b15-a7b9-3bf47dd1976c",
  "tables": {
    "applications": {
      "name": "applications",
      "columns": {
        "id": {
          "name": "id",
          "type": "int",
          "primaryKey": false,
          "notNull": true,
          "autoincrement": true
        },
        "fullName": {
          "name": "fullName",
          "type": "varchar(255)",
          "primaryKey": false,
          "notNull": true,
          "autoincrement": false
        },
        "email": {
          "name": "email",
          "type": "varchar(320)",
          "primaryKey": false,
          "notNull": true,
          "autoincrement": false
        },
        "phone": {
          "name": "phone",
          "type": "varchar(50)",
          "primaryKey": false,
          "notNull": true,
          "autoincrement": false
        },
        "country": {
          "name": "country",
          "type": "varchar(100)",
          "primaryKey": false,
          "notNull": true,
          "autoincrement": false
        },
        "city": {
          "name": "city",
          "type": "varchar(100)",
          "primaryKey": false,
          "notNull": true,
          "autoincrement": false
        },
        "track": {
          "name": "track",
          "type": "enum('technical','business')",
          "primaryKey": false,
          "notNull": true,
          "autoincrement": false
        },
        "careerPath": {
          "name": "careerPath",
          "type": "enum('egypt','uae','international','entrepreneurship')",
          "primaryKey": false,
          "notNull": true,
          "autoincrement": false
        },
        "education": {
          "name": "education",
          "type": "text",
          "primaryKey": false,
          "notNull": true,
          "autoincrement": false
        },
        "currentRole": {
          "name": "currentRole",
          "type": "varchar(255)",
          "primaryKey": false,
          "notNull": false,
          "autoincrement": false
        },
        "yearsExperience": {
          "name": "yearsExperience",
          "type": "int",
          "primaryKey": false,
          "notNull": false,
          "autoincrement": false
        },
        "technicalBackground": {
          "name": "technicalBackground",
          "type": "text",
          "primaryKey": false,
          "notNull": false,
          "autoincrement": false
        },
        "motivation": {
          "name": "motivation",
          "type": "text",
          "primaryKey": false,
          "notNull": true,
          "autoincrement": false
        },
        "goals": {
          "name": "goals",
          "type": "text",
          "primaryKey": false,
          "notNull": true,
          "autoincrement": false
        },
        "linkedinUrl": {
          "name": "linkedinUrl",
          "type": "varchar(500)",
          "primaryKey": false,
          "notNull": false,
          "autoincrement": false
        },
        "portfolioUrl": {
          "name": "portfolioUrl",
          "type": "varchar(500)",
          "primaryKey": false,
          "notNull": false,
          "autoincrement": false
        },
        "status": {
          "name": "status",
          "type": "enum('pending','reviewing','accepted','rejected')",
          "primaryKey": false,
          "notNull": true,
          "autoincrement": false,
          "default": "'pending'"
        },
        "createdAt": {
          "name": "createdAt",
          "type": "timestamp",
          "primaryKey": false,
          "notNull": true,
          "autoincrement": false,
          "default": "(now())"
        },
        "updatedAt": {
          "name": "updatedAt",
          "type": "timestamp",
          "primaryKey": false,
          "notNull": true,
          "autoincrement": false,
          "onUpdate": true,
          "default": "(now())"
        }
      },
      "indexes": {},
      "foreignKeys": {},
      "compositePrimaryKeys": {
        "applications_id": {
          "name": "applications_id",
          "columns": [
            "id"
          ]
        }
      },
      "uniqueConstraints": {},
      "checkConstraint": {}
    },
    "budgets": {
      "name": "budgets",
      "columns": {
        "id": {
          "name": "id",
          "type": "int",
          "primaryKey": false,
          "notNull": true,
          "autoincrement": true
        },
        "name": {
          "name": "name",
          "type": "varchar(255)",
          "primaryKey": false,
          "notNull": true,
          "autoincrement": false
        },
        "category": {
          "name": "category",
          "type": "enum('operations','marketing','programs','hr','other')",
          "primaryKey": false,
          "notNull": true,
          "autoincrement": false
        },
        "allocated": {
          "name": "allocated",
          "type": "decimal(12,2)",
          "primaryKey": false,
          "notNull": true,
          "autoincrement": false
        },
        "spent": {
          "name": "spent",
          "type": "decimal(12,2)",
          "primaryKey": false,
          "notNull": false,
          "autoincrement": false,
          "default": "'0'"
        },
        "fiscalYear": {
          "name": "fiscalYear",
          "type": "int",
          "primaryKey": false,
          "notNull": true,
          "autoincrement": false
        },
        "status": {
          "name": "status",
          "type": "enum('active','closed')",
          "primaryKey": false,
          "notNull": false,
          "autoincrement": false,
          "default": "'active'"
        },
        "createdAt": {
          "name": "createdAt",
          "type": "timestamp",
          "primaryKey": false,
          "notNull": true,
          "autoincrement": false,
          "default": "(now())"
        },
        "updatedAt": {
          "name": "updatedAt",
          "type": "timestamp",
          "primaryKey": false,
          "notNull": true,
          "autoincrement": false,
          "onUpdate": true,
          "default": "(now())"
        }
      },
      "indexes": {},
      "foreignKeys": {},
      "compositePrimaryKeys": {
        "budgets_id": {
          "name": "budgets_id",
          "columns": [
            "id"
          ]
        }
      },
      "uniqueConstraints": {},
      "checkConstraint": {}
    },
    "cohorts": {
      "name": "cohorts",
      "columns": {
        "id": {
          "name": "id",
          "type": "int",
          "primaryKey": false,
          "notNull": true,
          "autoincrement": true
        },
        "name": {
          "name": "name",
          "type": "varchar(255)",
          "primaryKey": false,
          "notNull": true,
          "autoincrement": false
        },
        "code": {
          "name": "code",
          "type": "varchar(50)",
          "primaryKey": false,
          "notNull": true,
          "autoincrement": false
        },
        "startDate": {
          "name": "startDate",
          "type": "timestamp",
          "primaryKey": false,
          "notNull": true,
          "autoincrement": false
        },
        "endDate": {
          "name": "endDate",
          "type": "timestamp",
          "primaryKey": false,
          "notNull": true,
          "autoincrement": false
        },
        "capacity": {
          "name": "capacity",
          "type": "int",
          "primaryKey": false,
          "notNull": true,
          "autoincrement": false
        },
        "enrolled": {
          "name": "enrolled",
          "type": "int",
          "primaryKey": false,
          "notNull": false,
          "autoincrement": false,
          "default": 0
        },
        "status": {
          "name": "status",
          "type": "enum('planning','recruiting','active','completed')",
          "primaryKey": false,
          "notNull": false,
          "autoincrement": false,
          "default": "'planning'"
        },
        "location": {
          "name": "location",
          "type": "varchar(255)",
          "primaryKey": false,
          "notNull": false,
          "autoincrement": false
        },
        "description": {
          "name": "description",
          "type": "text",
          "primaryKey": false,
          "notNull": false,
          "autoincrement": false
        },
        "createdAt": {
          "name": "createdAt",
          "type": "timestamp",
          "primaryKey": false,
          "notNull": true,
          "autoincrement": false,
          "default": "(now())"
        },
        "updatedAt": {
          "name": "updatedAt",
          "type": "timestamp",
          "primaryKey": false,
          "notNull": true,
          "autoincrement": false,
          "onUpdate": true,
          "default": "(now())"
        }
      },
      "indexes": {},
      "foreignKeys": {},
      "compositePrimaryKeys": {
        "cohorts_id": {
          "name": "cohorts_id",
          "columns": [
            "id"
          ]
        }
      },
      "uniqueConstraints": {
        "cohorts_code_unique": {
          "name": "cohorts_code_unique",
          "columns": [
            "code"
          ]
        }
      },
      "checkConstraint": {}
    },
    "contacts": {
      "name": "contacts",
      "columns": {
        "id": {
          "name": "id",
          "type": "int",
          "primaryKey": false,
          "notNull": true,
          "autoincrement": true
        },
        "name": {
          "name": "name",
          "type": "varchar(255)",
          "primaryKey": false,
          "notNull": true,
          "autoincrement": false
        },
        "email": {
          "name": "email",
          "type": "varchar(320)",
          "primaryKey": false,
          "notNull": true,
          "autoincrement": false
        },
        "phone": {
          "name": "phone",
          "type": "varchar(50)",
          "primaryKey": false,
          "notNull": false,
          "autoincrement": false
        },
        "subject": {
          "name": "subject",
          "type": "varchar(255)",
          "primaryKey": false,
          "notNull": true,
          "autoincrement": false
        },
        "message": {
          "name": "message",
          "type": "text",
          "primaryKey": false,
          "notNull": true,
          "autoincrement": false
        },
        "status": {
          "name": "status",
          "type": "enum('new','in_progress','resolved')",
          "primaryKey": false,
          "notNull": true,
          "autoincrement": false,
          "default": "'new'"
        },
        "createdAt": {
          "name": "createdAt",
          "type": "timestamp",
          "primaryKey": false,
          "notNull": true,
          "autoincrement": false,
          "default": "(now())"
        },
        "updatedAt": {
          "name": "updatedAt",
          "type": "timestamp",
          "primaryKey": false,
          "notNull": true,
          "autoincrement": false,
          "onUpdate": true,
          "default": "(now())"
        }
      },
      "indexes": {},
      "foreignKeys": {},
      "compositePrimaryKeys": {
        "contacts_id": {
          "name": "contacts_id",
          "columns": [
            "id"
          ]
        }
      },
      "uniqueConstraints": {},
      "checkConstraint": {}
    },
    "expenses": {
      "name": "expenses",
      "columns": {
        "id": {
          "name": "id",
          "type": "int",
          "primaryKey": false,
          "notNull": true,
          "autoincrement": true
        },
        "budgetId": {
          "name": "budgetId",
          "type": "int",
          "primaryKey": false,
          "notNull": false,
          "autoincrement": false
        },
        "category": {
          "name": "category",
          "type": "varchar(100)",
          "primaryKey": false,
          "notNull": true,
          "autoincrement": false
        },
        "description": {
          "name": "description",
          "type": "text",
          "primaryKey": false,
          "notNull": true,
          "autoincrement": false
        },
        "amount": {
          "name": "amount",
          "type": "decimal(10,2)",
          "primaryKey": false,
          "notNull": true,
          "autoincrement": false
        },
        "expenseDate": {
          "name": "expenseDate",
          "type": "timestamp",
          "primaryKey": false,
          "notNull": true,
          "autoincrement": false
        },
        "vendor": {
          "name": "vendor",
          "type": "varchar(255)",
          "primaryKey": false,
          "notNull": false,
          "autoincrement": false
        },
        "status": {
          "name": "status",
          "type": "enum('pending','approved','paid')",
          "primaryKey": false,
          "notNull": false,
          "autoincrement": false,
          "default": "'pending'"
        },
        "createdAt": {
          "name": "createdAt",
          "type": "timestamp",
          "primaryKey": false,
          "notNull": true,
          "autoincrement": false,
          "default": "(now())"
        }
      },
      "indexes": {},
      "foreignKeys": {},
      "compositePrimaryKeys": {
        "expenses_id": {
          "name": "expenses_id",
          "columns": [
            "id"
          ]
        }
      },
      "uniqueConstraints": {},
      "checkConstraint": {}
    },
    "leads": {
      "name": "leads",
      "columns": {
        "id": {
          "name": "id",
          "type": "int",
          "primaryKey": false,
          "notNull": true,
          "autoincrement": true
        },
        "firstName": {
          "name": "firstName",
          "type": "varchar(100)",
          "primaryKey": false,
          "notNull": true,
          "autoincrement": false
        },
        "lastName": {
          "name": "lastName",
          "type": "varchar(100)",
          "primaryKey": false,
          "notNull": true,
          "autoincrement": false
        },
        "email": {
          "name": "email",
          "type": "varchar(255)",
          "primaryKey": false,
          "notNull": true,
          "autoincrement": false
        },
        "phone": {
          "name": "phone",
          "type": "varchar(50)",
          "primaryKey": false,
          "notNull": false,
          "autoincrement": false
        },
        "company": {
          "name": "company",
          "type": "varchar(255)",
          "primaryKey": false,
          "notNull": false,
          "autoincrement": false
        },
        "source": {
          "name": "source",
          "type": "enum('website','referral','event','social_media','partner','other')",
          "primaryKey": false,
          "notNull": false,
          "autoincrement": false,
          "default": "'website'"
        },
        "status": {
          "name": "status",
          "type": "enum('new','contacted','qualified','converted','lost')",
          "primaryKey": false,
          "notNull": false,
          "autoincrement": false,
          "default": "'new'"
        },
        "notes": {
          "name": "notes",
          "type": "text",
          "primaryKey": false,
          "notNull": false,
          "autoincrement": false
        },
        "createdAt": {
          "name": "createdAt",
          "type": "timestamp",
          "primaryKey": false,
          "notNull": true,
          "autoincrement": false,
          "default": "(now())"
        },
        "updatedAt": {
          "name": "updatedAt",
          "type": "timestamp",
          "primaryKey": false,
          "notNull": true,
          "autoincrement": false,
          "onUpdate": true,
          "default": "(now())"
        }
      },
      "indexes": {},
      "foreignKeys": {},
      "compositePrimaryKeys": {
        "leads_id": {
          "name": "leads_id",
          "columns": [
            "id"
          ]
        }
      },
      "uniqueConstraints": {},
      "checkConstraint": {}
    },
    "mentors": {
      "name": "mentors",
      "columns": {
        "id": {
          "name": "id",
          "type": "int",
          "primaryKey": false,
          "notNull": true,
          "autoincrement": true
        },
        "firstName": {
          "name": "firstName",
          "type": "varchar(100)",
          "primaryKey": false,
          "notNull": true,
          "autoincrement": false
        },
        "lastName": {
          "name": "lastName",
          "type": "varchar(100)",
          "primaryKey": false,
          "notNull": true,
          "autoincrement": false
        },
        "email": {
          "name": "email",
          "type": "varchar(255)",
          "primaryKey": false,
          "notNull": true,
          "autoincrement": false
        },
        "phone": {
          "name": "phone",
          "type": "varchar(50)",
          "primaryKey": false,
          "notNull": false,
          "autoincrement": false
        },
        "company": {
          "name": "company",
          "type": "varchar(255)",
          "primaryKey": false,
          "notNull": false,
          "autoincrement": false
        },
        "expertise": {
          "name": "expertise",
          "type": "text",
          "primaryKey": false,
          "notNull": false,
          "autoincrement": false
        },
        "bio": {
          "name": "bio",
          "type": "text",
          "primaryKey": false,
          "notNull": false,
          "autoincrement": false
        },
        "status": {
          "name": "status",
          "type": "enum('active','inactive')",
          "primaryKey": false,
          "notNull": false,
          "autoincrement": false,
          "default": "'active'"
        },
        "sessionsCompleted": {
          "name": "sessionsCompleted",
          "type": "int",
          "primaryKey": false,
          "notNull": false,
          "autoincrement": false,
          "default": 0
        },
        "createdAt": {
          "name": "createdAt",
          "type": "timestamp",
          "primaryKey": false,
          "notNull": true,
          "autoincrement": false,
          "default": "(now())"
        },
        "updatedAt": {
          "name": "updatedAt",
          "type": "timestamp",
          "primaryKey": false,
          "notNull": true,
          "autoincrement": false,
          "onUpdate": true,
          "default": "(now())"
        }
      },
      "indexes": {},
      "foreignKeys": {},
      "compositePrimaryKeys": {
        "mentors_id": {
          "name": "mentors_id",
          "columns": [
            "id"
          ]
        }
      },
      "uniqueConstraints": {
        "mentors_email_unique": {
          "name": "mentors_email_unique",
          "columns": [
            "email"
          ]
        }
      },
      "checkConstraint": {}
    },
    "newsletterSubscribers": {
      "name": "newsletterSubscribers",
      "columns": {
        "id": {
          "name": "id",
          "type": "int",
          "primaryKey": false,
          "notNull": true,
          "autoincrement": true
        },
        "email": {
          "name": "email",
          "type": "varchar(320)",
          "primaryKey": false,
          "notNull": true,
          "autoincrement": false
        },
        "name": {
          "name": "name",
          "type": "varchar(255)",
          "primaryKey": false,
          "notNull": false,
          "autoincrement": false
        },
        "isActive": {
          "name": "isActive",
          "type": "int",
          "primaryKey": false,
          "notNull": true,
          "autoincrement": false,
          "default": 1
        },
        "createdAt": {
          "name": "createdAt",
          "type": "timestamp",
          "primaryKey": false,
          "notNull": true,
          "autoincrement": false,
          "default": "(now())"
        },
        "unsubscribedAt": {
          "name": "unsubscribedAt",
          "type": "timestamp",
          "primaryKey": false,
          "notNull": false,
          "autoincrement": false
        }
      },
      "indexes": {},
      "foreignKeys": {},
      "compositePrimaryKeys": {
        "newsletterSubscribers_id": {
          "name": "newsletterSubscribers_id",
          "columns": [
            "id"
          ]
        }
      },
      "uniqueConstraints": {
        "newsletterSubscribers_email_unique": {
          "name": "newsletterSubscribers_email_unique",
          "columns": [
            "email"
          ]
        }
      },
      "checkConstraint": {}
    },
    "siteSettings": {
      "name": "siteSettings",
      "columns": {
        "id": {
          "name": "id",
          "type": "int",
          "primaryKey": false,
          "notNull": true,
          "autoincrement": true
        },
        "settingKey": {
          "name": "settingKey",
          "type": "varchar(100)",
          "primaryKey": false,
          "notNull": true,
          "autoincrement": false
        },
        "settingValue": {
          "name": "settingValue",
          "type": "text",
          "primaryKey": false,
          "notNull": false,
          "autoincrement": false
        },
        "settingType": {
          "name": "settingType",
          "type": "enum('text','url','image','number','json')",
          "primaryKey": false,
          "notNull": true,
          "autoincrement": false,
          "default": "'text'"
        },
        "updatedAt": {
          "name": "updatedAt",
          "type": "timestamp",
          "primaryKey": false,
          "notNull": true,
          "autoincrement": false,
          "onUpdate": true,
          "default": "(now())"
        }
      },
      "indexes": {},
      "foreignKeys": {},
      "compositePrimaryKeys": {
        "siteSettings_id": {
          "name": "siteSettings_id",
          "columns": [
            "id"
          ]
        }
      },
      "uniqueConstraints": {
        "siteSettings_settingKey_unique": {
          "name": "siteSettings_settingKey_unique",
          "columns": [
            "settingKey"
          ]
        }
      },
      "checkConstraint": {}
    },
    "users": {
      "name": "users",
      "columns": {
        "id": {
          "name": "id",
          "type": "int",
          "primaryKey": false,
          "notNull": true,
          "autoincrement": true
        },
        "openId": {
          "name": "openId",
          "type": "varchar(64)",
          "primaryKey": false,
          "notNull": true,
          "autoincrement": false
        },
        "name": {
          "name": "name",
          "type": "text",
          "primaryKey": false,
          "notNull": false,
          "autoincrement": false
        },
        "email": {
          "name": "email",
          "type": "varchar(320)",
          "primaryKey": false,
          "notNull": false,
          "autoincrement": false
        },
        "loginMethod": {
          "name": "loginMethod",
          "type": "varchar(64)",
          "primaryKey": false,
          "notNull": false,
          "autoincrement": false
        },
        "role": {
          "name": "role",
          "type": "enum('user','admin')",
          "primaryKey": false,
          "notNull": true,
          "autoincrement": false,
          "default": "'user'"
        },
        "createdAt": {
          "name": "createdAt",
          "type": "timestamp",
          "primaryKey": false,
          "notNull": true,
          "autoincrement": false,
          "default": "(now())"
        },
        "updatedAt": {
          "name": "updatedAt",
          "type": "timestamp",
          "primaryKey": false,
          "notNull": true,
          "autoincrement": false,
          "onUpdate": true,
          "default": "(now())"
        },
        "lastSignedIn": {
          "name": "lastSignedIn",
          "type": "timestamp",
          "primaryKey": false,
          "notNull": true,
          "autoincrement": false,
          "default": "(now())"
        }
      },
      "indexes": {},
      "foreignKeys": {},
      "compositePrimaryKeys": {
        "users_id": {
          "name": "users_id",
          "columns": [
            "id"
          ]
        }
      },
      "uniqueConstraints": {
        "users_openId_unique": {
          "name": "users_openId_unique",
          "columns": [
            "openId"
          ]
        }
      },
      "checkConstraint": {}
    },
    "webPages": {
      "name": "webPages",
      "columns": {
        "id": {
          "name": "id",
          "type": "int",
          "primaryKey": false,
          "notNull": true,
          "autoincrement": true
        },
        "slug": {
          "name": "slug",
          "type": "varchar(255)",
          "primaryKey": false,
          "notNull": true,
          "autoincrement": false
        },
        "title": {
          "name": "title",
          "type": "varchar(255)",
          "primaryKey": false,
          "notNull": true,
          "autoincrement": false
        },
        "content": {
          "name": "content",
          "type": "text",
          "primaryKey": false,
          "notNull": true,
          "autoincrement": false
        },
        "status": {
          "name": "status",
          "type": "enum('draft','published')",
          "primaryKey": false,
          "notNull": false,
          "autoincrement": false,
          "default": "'draft'"
        },
        "updatedBy": {
          "name": "updatedBy",
          "type": "varchar(100)",
          "primaryKey": false,
          "notNull": false,
          "autoincrement": false
        },
        "createdAt": {
          "name": "createdAt",
          "type": "timestamp",
          "primaryKey": false,
          "notNull": true,
          "autoincrement": false,
          "default": "(now())"
        },
        "updatedAt": {
          "name": "updatedAt",
          "type": "timestamp",
          "primaryKey": false,
          "notNull": true,
          "autoincrement": false,
          "onUpdate": true,
          "default": "(now())"
        }
      },
      "indexes": {},
      "foreignKeys": {},
      "compositePrimaryKeys": {
        "webPages_id": {
          "name": "webPages_id",
          "columns": [
            "id"
          ]
        }
      },
      "uniqueConstraints": {
        "webPages_slug_unique": {
          "name": "webPages_slug_unique",
          "columns": [
            "slug"
          ]
        }
      },
      "checkConstraint": {}
    }
  },
  "views": {},
  "_meta": {
    "schemas": {},
    "tables": {},
    "columns": {}
  },
  "internal": {
    "tables": {},
    "indexes": {}
  }
}